{
  "sample_rows": [
    {
      "BENUTZER_ID": "2DObDLprEqtNY7I",
      "ID": "T8uieQH938jho2",
      "EXTERNE_BENUTZER_ID": "tjFbD7oTW9f",
      "GERÄTE_ID": "hfjKzQfjAgUbEj",
      "APP_GRUPPE_ID": "OkIYT1HbF7u",
      "APP_GRUPPE_API_ID": "wuc1UTLJhcLyjh",
      "ZEIT": 1642994791,
      "DISPATCH_ID": "XgLcjNPMzcDkkD",
      "SENDEN_ID": "OWm2tUYW5rqZta",
      "KAMPAGNE_ID": "LzlnDxGnqtlrBI3",
      "NACHRICHT_VARIATIONS_ID": "DTnY5fsSipLzLCY",
      "KAMPAGNE_API_ID": "zPOTNdD3HxdomRl",
      "NACHRICHT_VARIATIONS_API_ID": "P11tJJkJNYK0o0",
      "CANVAS_ID": null,
      "CANVAS_VARIATIONS_ID": null,
      "CANVAS_SCHRITT_ID": null,
      "CANVAS_SCHRITT_NACHRICHT_VARIATIONS_ID": "1oOaakQMKIDI6S",
      "CANVAS_API_ID": null,
      "CANVAS_VARIATIONS_API_ID": "kZmMUspPHdqfWh",
      "CANVAS_SCHRITT_API_ID": null,
      "CANVAS_SCHRITT_NACHRICHT_VARIATIONS_API_ID": "uVUVaMQ55Jp2Nr",
      "GESCHLECHT": null,
      "LAND": "US",
      "ZEITZONE": "Asia/Singapore",
      "SPRACHE": "en",
      "BENUTZERDEFINIERTE_ZEICHENFOLGE_ATTRIBUTEN": "[\n  \"HYpxP1375l1udX\",\n  \"bR77hhuk4Bxzgl\",\n  \"zzreFgxLi23jlo\",\n  \"3IxQGshaX7jXVs\"\n]",
      "BENUTZERDEFINIERTE_BOOLEAN_ATTRIBUTEN": "[\n  true,\n  true,\n  true,\n  true\n]",
      "BENUTZERDEFINIERTE_ZEIT_ATTRIBUTEN": "[\n  1642977883,\n  1642976778,\n  1642978731,\n  1642975656\n]",
      "BENUTZERDEFINIERTE_FLOAT_ATTRIBUTEN": "[\n  1.642976532000000e+09,\n  1.642977045000000e+09,\n  1.642978054000000e+09,\n  1.642976598000000e+09\n]",
      "BENUTZERDEFINIERTE_ZAHL_ATTRIBUTEN": "[\n  1.642976224000000e+09,\n  1.642977246000000e+09,\n  1.642977147000000e+09,\n  1.642975913000000e+09\n]",
      "E_MAIL_ADRESSE": "q3m4By7I@gmail.com",
      "BENUTZER_AGENT": "zpwDJtY",
      "IP_POOL": "bZuc663wlWhi0n",
      "SF_ERSTELLT_AM": "2021-12-14 11:13:45.741000-08:00"
    },
    {
      "BENUTZER_ID": "2Rlh3n1vwzrIkPo",
      "ID": "Ut49v9nVVZp6Ki",
      "EXTERNE_BENUTZER_ID": "MxOuge8P8In",
      "GERÄTE_ID": "inFfRbzJcujk8d",
      "APP_GRUPPE_ID": "OkIYT1HbF7u",
      "APP_GRUPPE_API_ID": "ffPkBoYNRTxH8I",
      "ZEIT": 1647412028,
      "DISPATCH_ID": "V1ag9x5jUhPYn0",
      "SENDEN_ID": "6lJR7iAENaa1vt",
      "KAMPAGNE_ID": "PrWbN2ZH5DAWa8X",
      "NACHRICHT_VARIATIONS_ID": "ibqJ0IITMsAtfPO",
      "KAMPAGNE_API_ID": "sAaaag5GrUEnevB",
      "NACHRICHT_VARIATIONS_API_ID": "W5obewzvUi2oRv",
      "CANVAS_ID": null,
      "CANVAS_VARIATIONS_ID": null,
      "CANVAS_SCHRITT_ID": null,
      "CANVAS_SCHRITT_NACHRICHT_VARIATIONS_ID": "nxmgKPQ4m8H6GQ",
      "CANVAS_API_ID": null,
      "CANVAS_VARIATIONS_API_ID": "IJX83iEArFzUDV",
      "CANVAS_SCHRITT_API_ID": null,
      "CANVAS_SCHRITT_NACHRICHT_VARIATIONS_API_ID": "LYkemDI3xYgTT3",
      "GESCHLECHT": "F",
      "LAND": "US",
      "ZEITZONE": "Indian/Chagos",
      "SPRACHE": "en",
      "BENUTZERDEFINIERTE_ZEICHENFOLGE_ATTRIBUTEN": "[\n  \"qZjhgLaJnH29PL\",\n  \"5VV3HTwE2YhJID\",\n  \"pLfYHfuWGPVn0M\",\n  \"tLsVvWsamedjKn\"\n]",
      "BENUTZERDEFINIERTE_BOOLEAN_ATTRIBUTEN": "[\n  true,\n  true,\n  true,\n  true\n]",
      "BENUTZERDEFINIERTE_ZEIT_ATTRIBUTEN": "[\n  1647402973,\n  1647401517,\n  1647402022,\n  1647402199\n]",
      "BENUTZERDEFINIERTE_FLOAT_ATTRIBUTEN": "[\n  1.647403110000000e+09,\n  1.647399773000000e+09,\n  1.647402678000000e+09,\n  1.647401397000000e+09\n]",
      "BENUTZERDEFINIERTE_ZAHL_ATTRIBUTEN": "[\n  1.647401686000000e+09,\n  1.647403068000000e+09,\n  1.647400501000000e+09,\n  1.647401344000000e+09\n]",
      "E_MAIL_ADRESSE": "64IL6LsK@appboy-co.com",
      "BENUTZER_AGENT": "t8gcmUq",
      "IP_POOL": "VbmeiT2uaVwwJH",
      "SF_ERSTELLT_AM": "2021-12-14 11:13:55.339000-08:00"
    },
    {
      "BENUTZER_ID": "2RqPp64EMf7RHLY",
      "ID": "0AUwZtOYDZa7s6",
      "EXTERNE_BENUTZER_ID": "4mIGJIpXJqL",
      "GERÄTE_ID": "2dKyuOqgCAAQNj",
      "APP_GRUPPE_ID": "OkIYT1HbF7u",
      "APP_GRUPPE_API_ID": "2koJyn0PgCxU1w",
      "ZEIT": 1686528991,
      "DISPATCH_ID": "EWu2HMQoClKGF6",
      "SENDEN_ID": "pt6BbnOhhbwPnp",
      "KAMPAGNE_ID": "IJHwgDyd5hHi2Vn",
      "NACHRICHT_VARIATIONS_ID": "fejUTqqsgz2fyCk",
      "KAMPAGNE_API_ID": "53J0XDoFA6EgZ2i",
      "NACHRICHT_VARIATIONS_API_ID": "TdO77BMwXUhqTI",
      "CANVAS_ID": null,
      "CANVAS_VARIATIONS_ID": null,
      "CANVAS_SCHRITT_ID": null,
      "CANVAS_SCHRITT_NACHRICHT_VARIATIONS_ID": "qXgCHmMM8LnPIy",
      "CANVAS_API_ID": null,
      "CANVAS_VARIATIONS_API_ID": "72q0iWde9sgEPu",
      "CANVAS_SCHRITT_API_ID": null,
      "CANVAS_SCHRITT_NACHRICHT_VARIATIONS_API_ID": "WrylJkVc60m3d9",
      "GESCHLECHT": "F",
      "LAND": "US",
      "ZEITZONE": "America/New_York",
      "SPRACHE": "en",
      "BENUTZERDEFINIERTE_ZEICHENFOLGE_ATTRIBUTEN": "[\n  \"1vxgldqp6SwL06\",\n  \"K5ukKWYUSKfeeM\",\n  \"5dZt7wZNRAvQtk\",\n  \"CdNtSJhdYN3b4F\"\n]",
      "BENUTZERDEFINIERTE_BOOLEAN_ATTRIBUTEN": "[\n  true,\n  true,\n  true,\n  true\n]",
      "BENUTZERDEFINIERTE_ZEIT_ATTRIBUTEN": "[\n  1686514346,\n  1686516885,\n  1686515248,\n  1686516127\n]",
      "BENUTZERDEFINIERTE_FLOAT_ATTRIBUTEN": "[\n  1.686514287000000e+09,\n  1.686516627000000e+09,\n  1.686515172000000e+09,\n  1.686516383000000e+09\n]",
      "BENUTZERDEFINIERTE_ZAHL_ATTRIBUTEN": "[\n  1.686515138000000e+09,\n  1.686514346000000e+09,\n  1.686513832000000e+09,\n  1.686515577000000e+09\n]",
      "E_MAIL_ADRESSE": "Ru0B7Dal@example.com",
      "BENUTZER_AGENT": "pft97Dx",
      "IP_POOL": "CcwBEjs31RYvOe",
      "SF_ERSTELLT_AM": "2021-12-14 11:12:18.595000-08:00"
    },
    {
      "BENUTZER_ID": "037kMpr2YEOZ09y",
      "ID": "DGpbaxUb09X26K",
      "EXTERNE_BENUTZER_ID": "P7b45szUbRa",
      "GERÄTE_ID": "VYZ6pqYVr3z7LG",
      "APP_GRUPPE_ID": "OkIYT1HbF7u",
      "APP_GRUPPE_API_ID": "ZZgNmv4vFDcvY4",
      "ZEIT": 1665429881,
      "DISPATCH_ID": "C0WYpBwDDNV3mD",
      "SENDEN_ID": "srOFzDw0yxNhdu",
      "KAMPAGNE_ID": "vQgezopdbHgervI",
      "NACHRICHT_VARIATIONS_ID": "iHPxKdiqSLVlYEu",
      "KAMPAGNE_API_ID": "0fe47fYuTPgkhrm",
      "NACHRICHT_VARIATIONS_API_ID": "JvW38p9sg8gIDO",
      "CANVAS_ID": null,
      "CANVAS_VARIATIONS_ID": null,
      "CANVAS_SCHRITT_ID": null,
      "CANVAS_SCHRITT_NACHRICHT_VARIATIONS_ID": "DRDF5HCuz9mN6w",
      "CANVAS_API_ID": null,
      "CANVAS_VARIATIONS_API_ID": "Ii0yR92QCSQGcU",
      "CANVAS_SCHRITT_API_ID": null,
      "CANVAS_SCHRITT_NACHRICHT_VARIATIONS_API_ID": "ZycvAWS1RmrdX5",
      "GESCHLECHT": "F",
      "LAND": "US",
      "ZEITZONE": "America/New_York",
      "SPRACHE": "en",
      "BENUTZERDEFINIERTE_ZEICHENFOLGE_ATTRIBUTEN": "[\n  \"Gq1e6kw6Hzyc44\",\n  \"TcAGxse5S18ueH\",\n  \"l0RnPrVF6a9Osn\",\n  \"jaCscnIi57i0Xd\"\n]",
      "BENUTZERDEFINIERTE_BOOLEAN_ATTRIBUTEN": "[\n  true,\n  true,\n  true,\n  true\n]",
      "BENUTZERDEFINIERTE_ZEIT_ATTRIBUTEN": "[\n  1665403823,\n  1665406724,\n  1665406190,\n  1665406708\n]",
      "BENUTZERDEFINIERTE_FLOAT_ATTRIBUTEN": "[\n  1.665404783000000e+09,\n  1.665406400000000e+09,\n  1.665404626000000e+09,\n  1.665405857000000e+09\n]",
      "BENUTZERDEFINIERTE_ZAHL_ATTRIBUTEN": "[\n  1.665404659000000e+09,\n  1.665405676000000e+09,\n  1.665406167000000e+09,\n  1.665404228000000e+09\n]",
      "E_MAIL_ADRESSE": "7h7mKWTt@example.com",
      "BENUTZER_AGENT": "Ah4XfCS",
      "IP_POOL": "rIXAz1jOTC2Ecd",
      "SF_ERSTELLT_AM": "2021-12-14 11:12:08.213000-08:00"
    },
    {
      "BENUTZER_ID": "1MOAwM3wBryPHR5",
      "ID": "oSxEipJizFnUET",
      "EXTERNE_BENUTZER_ID": "CJhfz3e0bNE",
      "GERÄTE_ID": "eYmEWiZ1gH2kB7",
      "APP_GRUPPE_ID": "OkIYT1HbF7u",
      "APP_GRUPPE_API_ID": "tgHWnjikQ9Iswg",
      "ZEIT": 1642203839,
      "DISPATCH_ID": "tdsp1koI5CLPIF",
      "SENDEN_ID": "fqGierOwRC0GqM",
      "KAMPAGNE_ID": "fbrybL0LvyTjTfY",
      "NACHRICHT_VARIATIONS_ID": "wwrzkBqp4aCtnHb",
      "KAMPAGNE_API_ID": "LHjOnYlGxxrgTMg",
      "NACHRICHT_VARIATIONS_API_ID": "E9xvkrEFBZGclD",
      "CANVAS_ID": null,
      "CANVAS_VARIATIONS_ID": null,
      "CANVAS_SCHRITT_ID": null,
      "CANVAS_SCHRITT_NACHRICHT_VARIATIONS_ID": "8DIJLp8KZ5teIL",
      "CANVAS_API_ID": null,
      "CANVAS_VARIATIONS_API_ID": "0FyG37exJJejZx",
      "CANVAS_SCHRITT_API_ID": null,
      "CANVAS_SCHRITT_NACHRICHT_VARIATIONS_API_ID": "oM68VPiH66yVA6",
      "GESCHLECHT": "M",
      "LAND": "US",
      "ZEITZONE": "Indian/Chagos",
      "SPRACHE": "en",
      "BENUTZERDEFINIERTE_ZEICHENFOLGE_ATTRIBUTEN": "[\n  \"AUFbnQ9J8baZ8z\",\n  \"t7uJTISAr203EB\",\n  \"evRAYFPTdeVvwd\",\n  \"Wysm4YNEHWo5Ew\"\n]",
      "BENUTZERDEFINIERTE_BOOLEAN_ATTRIBUTEN": "[\n  true,\n  true,\n  true,\n  true\n]",
      "BENUTZERDEFINIERTE_ZEIT_ATTRIBUTEN": "[\n  1642196537,\n  1642195393,\n  1642195671,\n  1642194793\n]",
      "BENUTZERDEFINIERTE_FLOAT_ATTRIBUTEN": "[\n  1.642196998000000e+09,\n  1.642197175000000e+09,\n  1.642197264000000e+09,\n  1.642196455000000e+09\n]",
      "BENUTZERDEFINIERTE_ZAHL_ATTRIBUTEN": "[\n  1.642197081000000e+09,\n  1.642195869000000e+09,\n  1.642196405000000e+09,\n  1.642195544000000e+09\n]",
      "E_MAIL_ADRESSE": "KWLqLs66@braze-inc.com",
      "BENUTZER_AGENT": "D81nYxb",
      "IP_POOL": "eqiEmKlgyBjSVV",
      "SF_ERSTELLT_AM": "2021-12-14 11:13:45.660000-08:00"
    }
  ],
  "table_name": "USERS_MESSAGES_EMAIL_OPEN_VIEW",
  "table_fullname": "BRAZE_USER_EVENT_DEMO_DATASET.PUBLIC.USERS_MESSAGES_EMAIL_OPEN_VIEW",
  "column_names": [
    "BENUTZERDEFINIERTE_FLOAT_ATTRIBUTEN",
    "KAMPAGNE_ID",
    "KAMPAGNE_API_ID",
    "LAND",
    "E_MAIL_ADRESSE",
    "SENDEN_ID",
    "CANVAS_SCHRITT_NACHRICHT_VARIATIONS_ID",
    "SPRACHE",
    "ZEIT",
    "BENUTZERDEFINIERTE_BOOLEAN_ATTRIBUTEN",
    "EXTERNE_BENUTZER_ID",
    "GESCHLECHT",
    "BENUTZERDEFINIERTE_ZAHL_ATTRIBUTEN",
    "NACHRICHT_VARIATIONS_ID",
    "DISPATCH_ID",
    "CANVAS_SCHRITT_API_ID",
    "ID",
    "APP_GRUPPE_ID",
    "GERÄTE_ID",
    "CANVAS_ID",
    "APP_GRUPPE_API_ID",
    "CANVAS_VARIATIONS_API_ID",
    "BENUTZERDEFINIERTE_ZEICHENFOLGE_ATTRIBUTEN",
    "IP_POOL",
    "NACHRICHT_VARIATIONS_API_ID",
    "CANVAS_SCHRITT_NACHRICHT_VARIATIONS_API_ID",
    "CANVAS_SCHRITT_ID",
    "CANVAS_API_ID",
    "BENUTZER_AGENT",
    "SF_ERSTELLT_AM",
    "BENUTZERDEFINIERTE_ZEIT_ATTRIBUTEN",
    "CANVAS_VARIATIONS_ID",
    "ZEITZONE",
    "BENUTZER_ID"
  ],
  "column_types": [
    "ARRAY",
    "TEXT",
    "TEXT",
    "TEXT",
    "TEXT",
    "TEXT",
    "TEXT",
    "TEXT",
    "NUMBER",
    "ARRAY",
    "TEXT",
    "TEXT",
    "ARRAY",
    "TEXT",
    "TEXT",
    "TEXT",
    "TEXT",
    "TEXT",
    "TEXT",
    "TEXT",
    "TEXT",
    "TEXT",
    "ARRAY",
    "TEXT",
    "TEXT",
    "TEXT",
    "TEXT",
    "TEXT",
    "TEXT",
    "TIMESTAMP_LTZ",
    "ARRAY",
    "TEXT",
    "TEXT",
    "TEXT"
  ],
  "description": [
    null,
    null,
    null,
    null,
    null,
    null,
    null,
    null,
    null,
    null,
    null,
    null,
    null,
    null,
    null,
    null,
    null,
    null,
    null,
    null,
    null,
    null,
    null,
    null,
    null,
    null,
    null,
    null,
    null,
    null,
    null,
    null,
    null,
    null
  ]
}