{
  "table_name": "DATASETS",
  "table_fullname": "META_KAGGLE.META_KAGGLE.DATASETS",
  "column_names": [
    "DateDerniereActivite",
    "Id",
    "IdUtilisateurProprietaire",
    "Type",
    "TelechargementsTotaux",
    "TotalVotes",
    "IdVersionActuelleDeLaSourceDeDonnees",
    "TotalKernels",
    "VuesTotales",
    "IdForum",
    "IdOrganisationProprietaire",
    "IdUtilisateurCreateur",
    "IdVersionActuelleDuJeuDeDonnees",
    "DateDeCreation"
  ],
  "column_types": [
    "DATE",
    "NUMBER",
    "NUMBER",
    "TEXT",
    "NUMBER",
    "NUMBER",
    "NUMBER",
    "NUMBER",
    "NUMBER",
    "NUMBER",
    "NUMBER",
    "NUMBER",
    "NUMBER",
    "NUMBER"
  ],
  "description": [
    null,
    null,
    null,
    null,
    null,
    null,
    null,
    null,
    null,
    null,
    null,
    null,
    null,
    null
  ],
  "sample_rows": [
    {
      "Id": 58151,
      "IdUtilisateurCreateur": 2311653,
      "IdUtilisateurProprietaire": 2311653,
      "IdOrganisationProprietaire": null,
      "IdVersionActuelleDuJeuDeDonnees": 112840,
      "IdVersionActuelleDeLaSourceDeDonnees": 123254,
      "IdForum": 66990,
      "Type": "Dataset",
      "DateDeCreation": 1538462902000000,
      "DateDerniereActivite": "2018-10-02",
      "VuesTotales": 132,
      "TelechargementsTotaux": 0,
      "TotalVotes": 0,
      "TotalKernels": 0
    },
    {
      "Id": 58161,
      "IdUtilisateurCreateur": 2311653,
      "IdUtilisateurProprietaire": 2311653,
      "IdOrganisationProprietaire": null,
      "IdVersionActuelleDuJeuDeDonnees": 112865,
      "IdVersionActuelleDeLaSourceDeDonnees": 123281,
      "IdForum": 67000,
      "Type": "Dataset",
      "DateDeCreation": 1538464192000000,
      "DateDerniereActivite": "2018-10-02",
      "VuesTotales": 10,
      "TelechargementsTotaux": 0,
      "TotalVotes": 0,
      "TotalKernels": 0
    },
    {
      "Id": 58185,
      "IdUtilisateurCreateur": 2311653,
      "IdUtilisateurProprietaire": 2311653,
      "IdOrganisationProprietaire": null,
      "IdVersionActuelleDuJeuDeDonnees": 112907,
      "IdVersionActuelleDeLaSourceDeDonnees": 123332,
      "IdForum": 67025,
      "Type": "Dataset",
      "DateDeCreation": 1538468032000000,
      "DateDerniereActivite": "2018-10-02",
      "VuesTotales": 13,
      "TelechargementsTotaux": 0,
      "TotalVotes": 0,
      "TotalKernels": 1
    },
    {
      "Id": 58199,
      "IdUtilisateurCreateur": 2311653,
      "IdUtilisateurProprietaire": 2311653,
      "IdOrganisationProprietaire": null,
      "IdVersionActuelleDuJeuDeDonnees": 112931,
      "IdVersionActuelleDeLaSourceDeDonnees": 123357,
      "IdForum": 67040,
      "Type": "Dataset",
      "DateDeCreation": 1538469809000000,
      "DateDerniereActivite": "2018-10-02",
      "VuesTotales": 314,
      "TelechargementsTotaux": 0,
      "TotalVotes": 0,
      "TotalKernels": 0
    },
    {
      "Id": 58252,
      "IdUtilisateurCreateur": 2312500,
      "IdUtilisateurProprietaire": 2312500,
      "IdOrganisationProprietaire": null,
      "IdVersionActuelleDuJeuDeDonnees": 113034,
      "IdVersionActuelleDeLaSourceDeDonnees": 123463,
      "IdForum": 67095,
      "Type": "Dataset",
      "DateDeCreation": 1538480351000000,
      "DateDerniereActivite": "2018-10-02",
      "VuesTotales": 63,
      "TelechargementsTotaux": 0,
      "TotalVotes": 0,
      "TotalKernels": 0
    }
  ]
}