{
  "sample_rows": [
    {
      "id": 174935,
      "id_api_fifa_joueur": 189263,
      "id_api_joueur": 102301,
      "date": "2010-08-30 00:00:00",
      "note_générale": 66,
      "potentiel": 77,
      "pied_préféré": "right",
      "rythme_de_travail_en_attaque": "medium",
      "rythme_de_travail_en_défense": "medium",
      "centres": 61,
      "finition": 66,
      "précision_de_tête": 60,
      "passes_courtes": 66,
      "volées": 62,
      "dribble": 72,
      "courbe": 43,
      "précision_des_coups_francs": 50,
      "passes_longues": 54,
      "contrôle_de_balle": 66,
      "accélération": 73,
      "vitesse_de_pointe": 75,
      "agilité": 75,
      "réactions": 64,
      "équilibre": 52,
      "puissance_de_tir": 65,
      "détente": 42,
      "endurance": 64,
      "force": 58,
      "tirs_loin": 57,
      "agressivité": 38,
      "interceptions": 30,
      "positionnement": 69,
      "vision": 51,
      "penalties": 57,
      "marquage": 11,
      "tackle_debout": 11,
      "tackle_à_glissade": 12,
      "plongeon_gardien": 6,
      "maniement_gardien": 13,
      "relance_gardien": 5,
      "positionnement_gardien": 5,
      "réflexes_gardien": 13
    },
    {
      "id": 94567,
      "id_api_fifa_joueur": 183142,
      "id_api_joueur": 47413,
      "date": "2014-09-18 00:00:00",
      "note_générale": 63,
      "potentiel": 64,
      "pied_préféré": "right",
      "rythme_de_travail_en_attaque": "medium",
      "rythme_de_travail_en_défense": "medium",
      "centres": 61,
      "finition": 60,
      "précision_de_tête": 52,
      "passes_courtes": 64,
      "volées": 46,
      "dribble": 57,
      "courbe": 34,
      "précision_des_coups_francs": 31,
      "passes_longues": 61,
      "contrôle_de_balle": 59,
      "accélération": 80,
      "vitesse_de_pointe": 81,
      "agilité": 75,
      "réactions": 59,
      "équilibre": 73,
      "puissance_de_tir": 59,
      "détente": 47,
      "endurance": 73,
      "force": 72,
      "tirs_loin": 54,
      "agressivité": 64,
      "interceptions": 48,
      "positionnement": 58,
      "vision": 64,
      "penalties": 59,
      "marquage": 64,
      "tackle_debout": 60,
      "tackle_à_glissade": 58,
      "plongeon_gardien": 15,
      "maniement_gardien": 13,
      "relance_gardien": 14,
      "positionnement_gardien": 14,
      "réflexes_gardien": 8
    },
    {
      "id": 158917,
      "id_api_fifa_joueur": 152697,
      "id_api_joueur": 34206,
      "date": "2010-08-30 00:00:00",
      "note_générale": 63,
      "potentiel": 68,
      "pied_préféré": "right",
      "rythme_de_travail_en_attaque": "medium",
      "rythme_de_travail_en_défense": "medium",
      "centres": 28,
      "finition": 28,
      "précision_de_tête": 64,
      "passes_courtes": 62,
      "volées": 34,
      "dribble": 45,
      "courbe": 21,
      "précision_des_coups_francs": 20,
      "passes_longues": 46,
      "contrôle_de_balle": 57,
      "accélération": 64,
      "vitesse_de_pointe": 61,
      "agilité": 49,
      "réactions": 56,
      "équilibre": 68,
      "puissance_de_tir": 46,
      "détente": 79,
      "endurance": 75,
      "force": 78,
      "tirs_loin": 21,
      "agressivité": 71,
      "interceptions": 66,
      "positionnement": 22,
      "vision": 55,
      "penalties": 33,
      "marquage": 58,
      "tackle_debout": 66,
      "tackle_à_glissade": 46,
      "plongeon_gardien": 5,
      "maniement_gardien": 9,
      "relance_gardien": 6,
      "positionnement_gardien": 8,
      "réflexes_gardien": 13
    },
    {
      "id": 142,
      "id_api_fifa_joueur": 221280,
      "id_api_joueur": 564793,
      "date": "2015-12-17 00:00:00",
      "note_générale": 61,
      "potentiel": 76,
      "pied_préféré": "right",
      "rythme_de_travail_en_attaque": "medium",
      "rythme_de_travail_en_défense": "high",
      "centres": 48,
      "finition": 32,
      "précision_de_tête": 47,
      "passes_courtes": 64,
      "volées": 34,
      "dribble": 54,
      "courbe": 56,
      "précision_des_coups_francs": 40,
      "passes_longues": 64,
      "contrôle_de_balle": 63,
      "accélération": 69,
      "vitesse_de_pointe": 67,
      "agilité": 60,
      "réactions": 61,
      "équilibre": 80,
      "puissance_de_tir": 53,
      "détente": 71,
      "endurance": 68,
      "force": 59,
      "tirs_loin": 38,
      "agressivité": 75,
      "interceptions": 54,
      "positionnement": 39,
      "vision": 61,
      "penalties": 42,
      "marquage": 52,
      "tackle_debout": 58,
      "tackle_à_glissade": 57,
      "plongeon_gardien": 8,
      "maniement_gardien": 13,
      "relance_gardien": 14,
      "positionnement_gardien": 14,
      "réflexes_gardien": 15
    },
    {
      "id": 98247,
      "id_api_fifa_joueur": 205174,
      "id_api_joueur": 208280,
      "date": "2013-02-22 00:00:00",
      "note_générale": 60,
      "potentiel": 65,
      "pied_préféré": "right",
      "rythme_de_travail_en_attaque": "medium",
      "rythme_de_travail_en_défense": "medium",
      "centres": 27,
      "finition": 37,
      "précision_de_tête": 61,
      "passes_courtes": 46,
      "volées": 31,
      "dribble": 27,
      "courbe": 18,
      "précision_des_coups_francs": 37,
      "passes_longues": 43,
      "contrôle_de_balle": 39,
      "accélération": 67,
      "vitesse_de_pointe": 70,
      "agilité": 59,
      "réactions": 61,
      "équilibre": 52,
      "puissance_de_tir": 37,
      "détente": 75,
      "endurance": 68,
      "force": 73,
      "tirs_loin": 42,
      "agressivité": 52,
      "interceptions": 52,
      "positionnement": 21,
      "vision": 41,
      "penalties": 42,
      "marquage": 61,
      "tackle_debout": 63,
      "tackle_à_glissade": 62,
      "plongeon_gardien": 13,
      "maniement_gardien": 10,
      "relance_gardien": 12,
      "positionnement_gardien": 14,
      "réflexes_gardien": 14
    }
  ],
  "table_name": "Player_Attributes",
  "table_fullname": "Player_Attributes",
  "column_names": [
    "id",
    "id_api_fifa_joueur",
    "id_api_joueur",
    "date",
    "note_générale",
    "potentiel",
    "pied_préféré",
    "rythme_de_travail_en_attaque",
    "rythme_de_travail_en_défense",
    "centres",
    "finition",
    "précision_de_tête",
    "passes_courtes",
    "volées",
    "dribble",
    "courbe",
    "précision_des_coups_francs",
    "passes_longues",
    "contrôle_de_balle",
    "accélération",
    "vitesse_de_pointe",
    "agilité",
    "réactions",
    "équilibre",
    "puissance_de_tir",
    "détente",
    "endurance",
    "force",
    "tirs_loin",
    "agressivité",
    "interceptions",
    "positionnement",
    "vision",
    "penalties",
    "marquage",
    "tackle_debout",
    "tackle_à_glissade",
    "plongeon_gardien",
    "maniement_gardien",
    "relance_gardien",
    "positionnement_gardien",
    "réflexes_gardien"
  ],
  "column_types": [
    "INTEGER",
    "INTEGER",
    "INTEGER",
    "TEXT",
    "INTEGER",
    "INTEGER",
    "TEXT",
    "TEXT",
    "TEXT",
    "INTEGER",
    "INTEGER",
    "INTEGER",
    "INTEGER",
    "INTEGER",
    "INTEGER",
    "INTEGER",
    "INTEGER",
    "INTEGER",
    "INTEGER",
    "INTEGER",
    "INTEGER",
    "INTEGER",
    "INTEGER",
    "INTEGER",
    "INTEGER",
    "INTEGER",
    "INTEGER",
    "INTEGER",
    "INTEGER",
    "INTEGER",
    "INTEGER",
    "INTEGER",
    "INTEGER",
    "INTEGER",
    "INTEGER",
    "INTEGER",
    "INTEGER",
    "INTEGER",
    "INTEGER",
    "INTEGER",
    "INTEGER",
    "INTEGER"
  ],
  "description": [
    "",
    "",
    "",
    "",
    "",
    "",
    "",
    "",
    "",
    "",
    "",
    "",
    "",
    "",
    "",
    "",
    "",
    "",
    "",
    "",
    "",
    "",
    "",
    "",
    "",
    "",
    "",
    "",
    "",
    "",
    "",
    "",
    "",
    "",
    "",
    "",
    "",
    "",
    "",
    "",
    "",
    ""
  ]
}