{
  "table_name": "PURCHASING_SUPPLIERS",
  "table_fullname": "WIDE_WORLD_IMPORTERS.WIDE_WORLD_IMPORTERS.PURCHASING_SUPPLIERS",
  "column_names": [
    "PostanschriftZeile1",
    "BankInternationalerCode",
    "PrimaryContactPersonID",
    "InterneKommentare",
    "BankkontonummerCode",
    "GueltigBis",
    "Lieferort",
    "Faxnummer",
    "GueltigVon",
    "PostanschriftZeile2",
    "LieferantID",
    "LastEditedBy",
    "LieferadresseZeile2",
    "LieferantReferenz",
    "LieferantKategorieID",
    "LiefermethodeID",
    "LieferortID",
    "LieferadresseZeile1",
    "Bankkontoname",
    "Postleitzahl",
    "Bankkontonummer",
    "Zahlungstage",
    "Telefonnummer",
    "LieferantName",
    "PostortID",
    "WebsiteURL",
    "Lieferpostleitzahl",
    "AlternateContactPersonID",
    "Bankfiliale"
  ],
  "column_types": [
    "TEXT",
    "NUMBER",
    "NUMBER",
    "TEXT",
    "NUMBER",
    "NUMBER",
    "FLOAT",
    "TEXT",
    "NUMBER",
    "TEXT",
    "NUMBER",
    "NUMBER",
    "TEXT",
    "TEXT",
    "NUMBER",
    "TEXT",
    "NUMBER",
    "TEXT",
    "TEXT",
    "NUMBER",
    "NUMBER",
    "NUMBER",
    "TEXT",
    "TEXT",
    "NUMBER",
    "TEXT",
    "NUMBER",
    "NUMBER",
    "TEXT"
  ],
  "description": [
    null,
    null,
    null,
    null,
    null,
    null,
    null,
    null,
    null,
    null,
    null,
    null,
    null,
    null,
    null,
    null,
    null,
    null,
    null,
    null,
    null,
    null,
    null,
    null,
    null,
    null,
    null,
    null,
    null
  ],
  "sample_rows": [
    {
      "LieferantID": 2,
      "LieferantName": "Contoso, Ltd.",
      "LieferantKategorieID": 2,
      "PrimaryContactPersonID": 23,
      "AlternateContactPersonID": 24,
      "LiefermethodeID": "9",
      "LieferortID": 13870,
      "PostortID": 13870,
      "LieferantReferenz": "B2084020",
      "Bankkontoname": "Contoso Ltd",
      "Bankfiliale": "Woodgrove Bank Greenbank",
      "BankkontonummerCode": 358698,
      "Bankkontonummer": 4587965215,
      "BankInternationalerCode": 25868,
      "Zahlungstage": 7,
      "InterneKommentare": "NULL",
      "Telefonnummer": "(360) 555-0100",
      "Faxnummer": "(360) 555-0101",
      "WebsiteURL": "http://www.contoso.com",
      "LieferadresseZeile1": "Unit 2",
      "LieferadresseZeile2": "2934 Night Road",
      "Lieferpostleitzahl": 98253,
      "Lieferort": 8.607660043233234e52,
      "PostanschriftZeile1": "PO Box 1012",
      "PostanschriftZeile2": "Jolimont",
      "Postleitzahl": 98253,
      "LastEditedBy": 1,
      "GueltigVon": 1356998700000000,
      "GueltigBis": 253402300799999999
    },
    {
      "LieferantID": 8,
      "LieferantName": "Lucerne Publishing",
      "LieferantKategorieID": 2,
      "PrimaryContactPersonID": 35,
      "AlternateContactPersonID": 36,
      "LiefermethodeID": "10",
      "LieferortID": 17161,
      "PostortID": 17161,
      "LieferantReferenz": "JQ082304802",
      "Bankkontoname": "Lucerne Publishing",
      "Bankfiliale": "Woodgrove Bank Jonesborough",
      "BankkontonummerCode": 654789,
      "Bankkontonummer": 3254123658,
      "BankInternationalerCode": 21569,
      "Zahlungstage": 30,
      "InterneKommentare": "NULL",
      "Telefonnummer": "(423) 555-0103",
      "Faxnummer": "(423) 555-0105",
      "WebsiteURL": "http://www.lucernepublishing.com",
      "LieferadresseZeile1": "Suite 34",
      "LieferadresseZeile2": "949482 Miller Boulevard",
      "Lieferpostleitzahl": 37659,
      "Lieferort": 8.607660043233227e52,
      "PostanschriftZeile1": "PO Box 8747",
      "PostanschriftZeile2": "Westerfold",
      "Postleitzahl": 37659,
      "LastEditedBy": 1,
      "GueltigVon": 1356998700000000,
      "GueltigBis": 253402300799999999
    },
    {
      "LieferantID": 10,
      "LieferantName": "Northwind Electric Cars",
      "LieferantKategorieID": 3,
      "PrimaryContactPersonID": 39,
      "AlternateContactPersonID": 40,
      "LiefermethodeID": "8",
      "LieferortID": 7899,
      "PostortID": 7899,
      "LieferantReferenz": "ML0300202",
      "Bankkontoname": "Northwind Electric Cars",
      "Bankfiliale": "Woodgrove Bank Crandon Lakes",
      "BankkontonummerCode": 325447,
      "Bankkontonummer": 3258786987,
      "BankInternationalerCode": 36214,
      "Zahlungstage": 30,
      "InterneKommentare": "NULL",
      "Telefonnummer": "(201) 555-0105",
      "Faxnummer": "(201) 555-0104",
      "WebsiteURL": "http://www.northwindelectriccars.com",
      "LieferadresseZeile1": null,
      "LieferadresseZeile2": "440 New Road",
      "Lieferpostleitzahl": 7860,
      "Lieferort": 8.60766004323322e52,
      "PostanschriftZeile1": "PO Box 30920",
      "PostanschriftZeile2": "Arlington",
      "Postleitzahl": 7860,
      "LastEditedBy": 1,
      "GueltigVon": 1356998700000000,
      "GueltigBis": 253402300799999999
    },
    {
      "LieferantID": 4,
      "LieferantName": "Fabrikam, Inc.",
      "LieferantKategorieID": 4,
      "PrimaryContactPersonID": 27,
      "AlternateContactPersonID": 28,
      "LiefermethodeID": "7",
      "LieferortID": 18557,
      "PostortID": 18557,
      "LieferantReferenz": "293092",
      "Bankkontoname": "Fabrikam Inc",
      "Bankfiliale": "Woodgrove Bank Lakeview Heights",
      "BankkontonummerCode": 789568,
      "Bankkontonummer": 4125863879,
      "BankInternationalerCode": 12546,
      "Zahlungstage": 30,
      "InterneKommentare": "NULL",
      "Telefonnummer": "(203) 555-0104",
      "Faxnummer": "(203) 555-0108",
      "WebsiteURL": "http://www.fabrikam.com",
      "LieferadresseZeile1": "Level 2",
      "LieferadresseZeile2": "393999 Woodberg Road",
      "Lieferpostleitzahl": 40351,
      "Lieferort": 8.607660043233223e52,
      "PostanschriftZeile1": "PO Box 301",
      "PostanschriftZeile2": "Eaglemont",
      "Postleitzahl": 40351,
      "LastEditedBy": 1,
      "GueltigVon": 1356998700000000,
      "GueltigBis": 253402300799999999
    },
    {
      "LieferantID": 11,
      "LieferantName": "Trey Research",
      "LieferantKategorieID": 8,
      "PrimaryContactPersonID": 41,
      "AlternateContactPersonID": 42,
      "LiefermethodeID": "NULL",
      "LieferortID": 17277,
      "PostortID": 17277,
      "LieferantReferenz": "082304822",
      "Bankkontoname": "Trey Research",
      "Bankfiliale": "Woodgrove Bank Kadoka",
      "BankkontonummerCode": 658968,
      "Bankkontonummer": 1254785321,
      "BankInternationalerCode": 56958,
      "Zahlungstage": 7,
      "InterneKommentare": "NULL",
      "Telefonnummer": "(605) 555-0103",
      "Faxnummer": "(605) 555-0101",
      "WebsiteURL": "http://www.treyresearch.net",
      "LieferadresseZeile1": "Level 43",
      "LieferadresseZeile2": "9401 Polar Avenue",
      "Lieferpostleitzahl": 57543,
      "Lieferort": 8.607660043233225e52,
      "PostanschriftZeile1": "PO  Box 595",
      "PostanschriftZeile2": "Port Fairy",
      "Postleitzahl": 57543,
      "LastEditedBy": 1,
      "GueltigVon": 1356998700000000,
      "GueltigBis": 253402300799999999
    }
  ]
}