{
  "table_name": "icoads_core_2014",
  "table_fullname": "bigquery-public-data.noaa_icoads.icoads_core_2014",
  "column_names": [
    "année",
    "mois",
    "jour",
    "heure",
    "latitude",
    "longitude",
    "imma_version",
    "attm_count",
    "indicateur_heure",
    "indicateur_latlong",
    "cap_bateau",
    "vitesse_bateau",
    "indicateur_source_nationale",
    "id_indicator",
    "callsign",
    "code_pays",
    "indicateur_direction_vent",
    "direction_vent_vrai",
    "indicateur_vitesse_vent",
    "vitesse_vent",
    "indicateur_visibilite",
    "visibilite",
    "temps_actuel",
    "temps_passe",
    "pression_niveau_mer",
    "caracteristique_ppp",
    "amt_pressure_tend",
    "indicateur_temp",
    "temperature_air",
    "wbt_indicator",
    "temperature_bulbe_humide",
    "dpt_indicator",
    "temperature_point_rosee",
    "sst_measurement_method",
    "temperature_surface_mer",
    "quantite_nuages_totale",
    "quantite_nuages_bas",
    "type_nuages_bas",
    "indicateur_hauteur_nuages",
    "hauteur_nuages",
    "type_nuages_moyens",
    "type_nuages_hauts",
    "direction_vague",
    "periode_vague",
    "hauteur_vague",
    "direction_houle",
    "periode_houle",
    "hauteur_houle",
    "box_system_indicator",
    "numero_boite_dix_degres",
    "numero_boite_un_degre",
    "deck",
    "source_id",
    "platform_type",
    "dup_status",
    "dup_check",
    "track_check",
    "pressure_bias",
    "wave_period_indicator",
    "swell_period_indicator",
    "second_country_code",
    "adaptive_qc_flags",
    "nightday_flag",
    "trimming_flags",
    "ncdc_qc_flags",
    "external",
    "landlocked_flag",
    "source_exclusion_flags",
    "unique_report_id",
    "release_no_primary",
    "release_no_secondary",
    "release_no_tertiary",
    "release_status_indicator",
    "intermediate_reject_flag",
    "timestamp"
  ],
  "column_types": [
    "INT64",
    "INT64",
    "INT64",
    "FLOAT64",
    "FLOAT64",
    "FLOAT64",
    "INT64",
    "INT64",
    "INT64",
    "INT64",
    "INT64",
    "INT64",
    "INT64",
    "INT64",
    "STRING",
    "STRING",
    "INT64",
    "INT64",
    "INT64",
    "FLOAT64",
    "INT64",
    "INT64",
    "INT64",
    "INT64",
    "FLOAT64",
    "INT64",
    "FLOAT64",
    "INT64",
    "FLOAT64",
    "INT64",
    "FLOAT64",
    "INT64",
    "FLOAT64",
    "INT64",
    "FLOAT64",
    "INT64",
    "INT64",
    "STRING",
    "INT64",
    "STRING",
    "STRING",
    "STRING",
    "INT64",
    "INT64",
    "FLOAT64",
    "INT64",
    "INT64",
    "FLOAT64",
    "STRING",
    "INT64",
    "INT64",
    "INT64",
    "INT64",
    "INT64",
    "INT64",
    "INT64",
    "INT64",
    "INT64",
    "INT64",
    "INT64",
    "INT64",
    "STRING",
    "INT64",
    "STRING",
    "STRING",
    "INT64",
    "INT64",
    "INT64",
    "STRING",
    "INT64",
    "INT64",
    "INT64",
    "INT64",
    "INT64",
    "TIMESTAMP"
  ],
  "nested_column_names": [
    "année",
    "mois",
    "jour",
    "heure",
    "latitude",
    "longitude",
    "imma_version",
    "attm_count",
    "indicateur_de_temps",
    "indicateur_de_latlong",
    "cap_de_navire",
    "vitesse_de_navire",
    "indicateur_de_source_nationale",
    "id_indicator",
    "callsign",
    "code_de_pays",
    "indicateur_de_direction_de_vent",
    "direction_de_vent_vrai",
    "indicateur_de_vitesse_de_vent",
    "vitesse_de_vent",
    "indicateur_de_visibilite",
    "visibilite",
    "temps_actuel",
    "temps_passe",
    "pression_au_niveau_de_la_mer",
    "caracteristique_de_ppp",
    "amt_pressure_tend",
    "indicateur_de_temperature",
    "temperature_de_lair",
    "wbt_indicator",
    "temperature_de_bulbe_humide",
    "dpt_indicator",
    "temperature_de_point_de_rosee",
    "methode_de_mesure_de_la_temp_de_surface_de_la_mer",
    "temperature_de_surface_de_la_mer",
    "quantite_de_nuages_totaux",
    "quantite_de_nuages_bas",
    "type_de_nuages_bas",
    "indicateur_de_hauteur_de_nuages",
    "hauteur_de_nuages",
    "type_de_nuages_moyens",
    "type_de_nuages_elevés",
    "direction_des_vagues",
    "periode_des_vagues",
    "hauteur_des_vagues",
    "direction_de_houle",
    "periode_de_houle",
    "hauteur_de_houle",
    "indicateur_de_systeme_de_boites",
    "numero_de_boite_de_dix_degres",
    "numero_de_boite_de_un_degre",
    "pont",
    "source_id",
    "type_de_plateforme",
    "statut_de_doublon",
    "verif_de_doublon",
    "verif_de_trajectoire",
    "biais_de_pression",
    "indicateur_de_periode_de_vagues",
    "indicateur_de_periode_de_houle",
    "second_code_de_pays",
    "flags_de_qc_adaptatif",
    "flag_jour_nuit",
    "flags_de_rognage",
    "flags_de_qc_ncdc",
    "externe",
    "flag_de_mer_interieure",
    "flags_dexclusion_de_source",
    "id_de_rapport_unique",
    "numero_de_liberation_primaire",
    "numero_de_liberation_secondaire",
    "numero_de_liberation_tertiaire",
    "indicateur_de_statut_de_liberation",
    "flag_de_rejet_intermediaire",
    "timestamp"
  ],
  "nested_column_types": [
    "INT64",
    "INT64",
    "INT64",
    "FLOAT64",
    "FLOAT64",
    "FLOAT64",
    "INT64",
    "INT64",
    "INT64",
    "INT64",
    "INT64",
    "INT64",
    "INT64",
    "INT64",
    "STRING",
    "STRING",
    "INT64",
    "INT64",
    "INT64",
    "FLOAT64",
    "INT64",
    "INT64",
    "INT64",
    "INT64",
    "FLOAT64",
    "INT64",
    "FLOAT64",
    "INT64",
    "FLOAT64",
    "INT64",
    "FLOAT64",
    "INT64",
    "FLOAT64",
    "INT64",
    "FLOAT64",
    "INT64",
    "INT64",
    "STRING",
    "INT64",
    "STRING",
    "STRING",
    "STRING",
    "INT64",
    "INT64",
    "FLOAT64",
    "INT64",
    "INT64",
    "FLOAT64",
    "STRING",
    "INT64",
    "INT64",
    "INT64",
    "INT64",
    "INT64",
    "INT64",
    "INT64",
    "INT64",
    "INT64",
    "INT64",
    "INT64",
    "INT64",
    "STRING",
    "INT64",
    "STRING",
    "STRING",
    "INT64",
    "INT64",
    "INT64",
    "STRING",
    "INT64",
    "INT64",
    "INT64",
    "INT64",
    "INT64",
    "TIMESTAMP"
  ],
  "description": [
    "Année du moment réel d'observation auquel le baromètre est lu. Il s'agit de 4 chiffres",
    "Mois du moment réel d'observation auquel le baromètre est lu. (1 = janvier, 2 = février, …, 12 = décembre)",
    "Jour du moment réel d'observation auquel le baromètre est lu. Jours 1-31",
    "Heure du moment réel d'observation auquel le baromètre est lu. Heures 0,00 à 23,99",
    "Position à la centaine de degré +N ou –S (mesurée au nord ou au sud de l'équateur) et +E ou −W (mesurée à l'est ou à l'ouest du méridien de Greenwich).",
    "Position à la centaine de degré +N ou –S (mesurée au nord ou au sud de l'équateur) et +E ou −W (mesurée à l'est ou à l'ouest du méridien de Greenwich).",
    "Version IMMA : 0 = 2010, 1 = 2016",
    "Le comptage attm : 0 – enregistrement abrégé (pas d'attm) 1 – un attm 2 – deux attms, etc.",
    "Indicateur de temps qui conserve la précision d'origine des champs de temps : 0 – heure la plus proche 1 – heure à la dizaine 2 – heure plus minutes 3 – haute résolution (par exemple, heure à la centaine)",
    "Indicateur de latlong qui conserve la précision à laquelle LAT et LON ont été enregistrés ou traduits, ou s'ils ont été dérivés plus tard par interpolation entre des positions connues : 0 – degrés et dizaines 1 – degrés entiers 2 – précision mixte 3 – interpolé 4 – degrés et minutes 5 – données à haute résolution (par exemple, degrés à la seconde) 6 – autre",
    "Vrai direction du déplacement résultant du navire pendant les trois heures précédant le moment d'observation (c'est-à-dire, cap du navire (vrai) effectué) : 0 – stationnaire (navire à l'ancre) 5 – SO 1 – NE 6 – O 2 – E 7 – NO 3 – SE 8 – N 4 – S 9 – inconnu",
    "Vitesse moyenne du navire effectuée pendant les trois heures précédant le moment d'observation (à partir du 1er janvier 1968) : 0 – 0 nœud  1 – 1-5 nœuds 2 – 6-10 nœuds 3 – 11-15 nœuds 4 – 16-20 nœuds  5 – 21-25 nœuds 6 – 26-30 nœuds 7 – 31-35 nœuds 8 – 36-40 nœuds 9 – plus de 40 nœuds.    Avant le 1er janvier 1968, un code différent pour VS, également avec une plage de 0-9, s'appliquait (Met Office 1948) : 0 – 0 nœud 1 – 1-3 nœuds 2 – 4-6 nœuds 3 – 7-9 nœuds 4 – 10-12 nœuds 5 – 13-15 nœuds  6 – 16-18 nœuds 7 – 19-21 nœuds 8 – 22-24 nœuds 9 – plus de 24 nœuds",
    "Un champ disponible pour une utilisation nationale dans l'identification des sous-ensembles de données.",
    "L'indicateur d'ID indique si un indicatif d'appel ou un autre type d'identification est contenu dans le champ ID (et dans les données R3.0, II doit toujours être présent lorsque des informations d'ID existent ; alors que II doit toujours être manquant si ID est manquant) : 0 – ID présent, mais type inconnu 1 – indicatif d'appel de navire, de station de vaisseau océanique (OSV) ou de station de glace 2 – ID générique (par exemple, NAVIRE, BOUEE, RIGG, PLAT) 3 – numéro de bouée à 5 chiffres de l'OMM 4 – autre numéro de bouée (par exemple, numéro de bouée Argos ou national) 5 – ID de réseau automatisé côtier et marin (C-MAN) (attribué par l'US NDBC ou d'autres organisations) 6 – nom ou numéro de station 7 – numéro de plateforme océanographique / croisière 8 – ID pseudo de navire de pêche 9 – numéro de navire national 10 – informations composites à partir de données de navire précoces 11 – ID de bouée à 7 chiffres (proposé)",
    "Identification / Indicatif d'appel",
    "Le pays qui a recruté un navire, qui peut différer du pays de réception immédiate (C2, champ 15) et peut également différer du registre du navire",
    "Indique la boussole (et la précision approximative) utilisée pour signaler la direction du vent : 0 – boussole à 36 points 1 – boussole à 32 points 2 – 16 des 36 points de la boussole 3 – 16 des 32 points de la boussole 4 – boussole à 8 points 5 – boussole à 360 points 6 – données à haute résolution (par exemple, dixièmes de degré)",
    "La direction (vraie) d'où vient le vent (ou va venir), stockée en degrés entiers (c'est-à-dire boussole à 360 points ; plage : 1-360°), ou codes spéciaux : 361 – calme 362 – variable, ou toutes les directions",
    "La vitesse du vent est stockée en dixièmes de mètre par seconde (pour conserver une précision adéquate pour les vents convertis à partir de nœuds, ou des données à haute résolution). WI montre les unités dans lesquelles et/ou la méthode par laquelle W a été enregistré à l'origine (0, 1, 3, 4 suivent le code OMM 1855) : 0 – mètre par seconde, estimé 53 1 – mètre par seconde, obtenu à partir d'un anémomètre (mesuré) 2 – estimé (unités d'origine inconnues) 3 – nœud, estimé 4 – nœud, obtenu à partir d'un anémomètre (mesuré) 5 – force de Beaufort (basée sur la documentation) 6 – estimé (unités d'origine inconnues)/méthode inconnue 7 – mesuré (unités d'origine inconnues) 8 – mesure à haute résolution (par exemple, centièmes de mètre par seconde)",
    "Vitesse du vent qui est stockée en dixièmes de mètre par seconde (pour conserver une précision adéquate pour les vents convertis à partir de nœuds, ou des données à haute résolution)",
    "indique si la visibilité était : 0 – estimée (ou méthode d'observation inconnue) 1 – mesurée 2 – brouillard présent (obsolète)",
    "Visibilité (visibilité horizontale à la surface en kilomètres) selon le code OMM 4377 à partir duquel, dans la signalisation de la visibilité en mer, l'OMM (2009a ; Reg. 12.2.1.3.2) indique que la décile 90-99 doit être utilisée (de plus, Reg. 12.2.1.3.1 : lorsque la visibilité horizontale n'est pas la même dans différentes directions, la distance la plus courte doit être donnée pour VV) : 90 – moins de 0,05 kilomètre 91 – 0,05 92 – 0,2 93 – 0,5 94 – 1 95 – 2 96 – 4 97 – 10 98 – 20 99 – 50 ou plus",
    "Codes OMM 4677 (Table D3) pour WW, et 4561 pour W1 : 0 – nuages couvrant 1/2 ou moins du ciel pendant la période appropriée 1 – nuages couvrant plus de 1/2 du ciel pendant une partie de la période appropriée et couvrant 1",
    "",
    "",
    "",
    "",
    "",
    "",
    "",
    "",
    "",
    "",
    "",
    "",
    "",
    "",
    "",
    "",
    "",
    "",
    "",
    "",
    "",
    "",
    "",
    "",
    "",
    "",
    "",
    "",
    "",
    "",
    "",
    "",
    "",
    "",
    "",
    "",
    "",
    "",
    "",
    "",
    "",
    "",
    "",
    "",
    "",
    "",
    "",
    "",
    "",
    "",
    "",
    ""
  ],
  "sample_rows": [
    {
      "année": 2014,
      "mois": 12,
      "jour": 4,
      "heure": 5.0,
      "latitude": 19.3,
      "longitude": -66.5,
      "imma_version": 1,
      "attm_count": 4,
      "indicateur_de_temps": 0,
      "indicateur_de_latlong": 0,
      "cap_de_navire": 7,
      "vitesse_de_navire": 4,
      "indicateur_de_source_nationale": null,
      "id_indicator": 0,
      "callsign": "GL",
      "code_de_pays": "",
      "indicateur_de_direction_de_vent": 0,
      "direction_de_vent_vrai": 70,
      "indicateur_de_vitesse_de_vent": 3,
      "vitesse_de_vent": 10.3,
      "indicateur_de_visibilite": null,
      "visibilite": 98,
      "temps_actuel": 80,
      "temps_passe": 1,
      "pression_au_niveau_de_la_mer": 1021.0,
      "caracteristique_de_ppp": 4,
      "amt_pressure_tend": 0.0,
      "indicateur_de_temperature": 0,
      "temperature_de_lair": 25.0,
      "wbt_indicator": 0,
      "temperature_de_bulbe_humide": 22.0,
      "dpt_indicator": null,
      "temperature_de_point_de_rosee": 20.7,
      "methode_de_mesure_de_la_temp_de_surface_de_la_mer": 3,
      "temperature_de_surface_de_la_mer": 27.0,
      "quantite_de_nuages_totaux": 1,
      "quantite_de_nuages_bas": 1,
      "type_de_nuages_bas": "2",
      "indicateur_de_hauteur_de_nuages": null,
      "hauteur_de_nuages": "7",
      "type_de_nuages_moyens": "A",
      "type_de_nuages_elevés": "A",
      "direction_des_vagues": null,
      "periode_des_vagues": 2,
      "hauteur_des_vagues": 2.5,
      "direction_de_houle": 1,
      "periode_de_houle": 2,
      "hauteur_de_houle": 2.5,
      "indicateur_de_systeme_de_boites": "",
      "numero_de_boite_de_dix_degres": 279,
      "numero_de_boite_de_un_degre": 96,
      "pont": 992,
      "source_id": 114,
      "type_de_plateforme": 5,
      "statut_de_doublon": 1,
      "verif_de_doublon": 2,
      "verif_de_trajectoire": null,
      "biais_de_pression": null,
      "indicateur_de_periode_de_vagues": null,
      "indicateur_de_periode_de_houle": null,
      "second_code_de_pays": null,
      "flags_de_qc_adaptatif": "",
      "flag_jour_nuit": 1,
      "flags_de_rognage": "111111",
      "flags_de_qc_ncdc": "11111111111111",
      "externe": null,
      "flag_de_mer_interieure": null,
      "flags_dexclusion_de_source": null,
      "id_de_rapport_unique": "CVFDFZ",
      "numero_de_liberation_primaire": 3,
      "numero_de_liberation_secondaire": 0,
      "numero_de_liberation_tertiaire": 0,
      "indicateur_de_statut_de_liberation": 2,
      "flag_de_rejet_intermediaire": 1,
      "timestamp": "2014-12-04 05:00:00+00:00"
    },
    {
      "année": 2014,
      "mois": 11,
      "jour": 24,
      "heure": 1.0,
      "latitude": -11.0,
      "longitude": 142.8,
      "imma_version": 1,
      "attm_count": 4,
      "indicateur_de_temps": 0,
      "indicateur_de_latlong": 0,
      "cap_de_navire": 8,
      "vitesse_de_navire": 4,
      "indicateur_de_source_nationale": null,
      "id_indicator": 0,
      "callsign": "CEL",
      "code_de_pays": "",
      "indicateur_de_direction_de_vent": 0,
      "direction_de_vent_vrai": 120,
      "indicateur_de_vitesse_de_vent": 3,
      "vitesse_de_vent": 10.3,
      "indicateur_de_visibilite": null,
      "visibilite": 97,
      "temps_actuel": 0,
      "temps_passe": 0,
      "pression_au_niveau_de_la_mer": 1011.7,
      "caracteristique_de_ppp": 0,
      "amt_pressure_tend": 0.0,
      "indicateur_de_temperature": 0,
      "temperature_de_lair": 29.3,
      "wbt_indicator": 0,
      "temperature_de_bulbe_humide": 24.8,
      "dpt_indicator": null,
      "temperature_de_point_de_rosee": 22.8,
      "methode_de_mesure_de_la_temp_de_surface_de_la_mer": 1,
      "temperature_de_surface_de_la_mer": 27.8,
      "quantite_de_nuages_totaux": 7,
      "quantite_de_nuages_bas": 2,
      "type_de_nuages_bas": "4",
      "indicateur_de_hauteur_de_nuages": null,
      "hauteur_de_nuages": "4",
      "type_de_nuages_moyens": "4",
      "type_de_nuages_elevés": "1",
      "direction_des_vagues": null,
      "periode_des_vagues": 2,
      "hauteur_des_vagues": 1.0,
      "direction_de_houle": 0,
      "periode_de_houle": 0,
      "hauteur_de_houle": 0.0,
      "indicateur_de_systeme_de_boites": "",
      "numero_de_boite_de_dix_degres": 372,
      "numero_de_boite_de_un_degre": 12,
      "pont": 992,
      "source_id": 114,
      "type_de_plateforme": 5,
      "statut_de_doublon": 1,
      "verif_de_doublon": 2,
      "verif_de_trajectoire": null,
      "biais_de_pression": null,
      "indicateur_de_periode_de_vagues": null,
      "indicateur_de_periode_de_houle": null,
      "second_code_de_pays": null,
      "flags_de_qc_adaptatif": "",
      "flag_jour_nuit": 2,
      "flags_de_rognage": "111111",
      "flags_de_qc_ncdc": "11111111111111",
      "externe": null,
      "flag_de_mer_interieure": null,
      "flags_dexclusion_de_source": null,
      "id_de_rapport_unique": "CU1Q59",
      "numero_de_liberation_primaire": 3,
      "numero_de_liberation_secondaire": 0,
      "numero_de_liberation_tertiaire": 0,
      "indicateur_de_statut_de_liberation": 2,
      "flag_de_rejet_intermediaire": 1,
      "timestamp": "2014-11-24 01:00:00+00:00"
    },
    {
      "année": 2014,
      "mois": 11,
      "jour": 29,
      "heure": 2.0,
      "latitude": -4.6,
      "longitude": 112.4,
      "imma_version": 1,
      "attm_count": 4,
      "indicateur_de_temps": 0,
      "indicateur_de_latlong": 0,
      "cap_de_navire": 6,
      "vitesse_de_navire": 3,
      "indicateur_de_source_nationale": null,
      "id_indicator": 0,
      "callsign": "CEL",
      "code_de_pays": "",
      "indicateur_de_direction_de_vent": 0,
      "direction_de_vent_vrai": 260,
      "indicateur_de_vitesse_de_vent": 3,
      "vitesse_de_vent": 1.0,
      "indicateur_de_visibilite": null,
      "visibilite": 98,
      "temps_actuel": 2,
      "temps_passe": 2,
      "pression_au_niveau_de_la_mer": 1009.3,
      "caracteristique_de_ppp": 1,
      "amt_pressure_tend": 1.3,
      "indicateur_de_temperature": 0,
      "temperature_de_lair": 31.6,
      "wbt_indicator": 0,
      "temperature_de_bulbe_humide": 26.8,
      "dpt_indicator": null,
      "temperature_de_point_de_rosee": 24.8,
      "methode_de_mesure_de_la_temp_de_surface_de_la_mer": 1,
      "temperature_de_surface_de_la_mer": 30.4,
      "quantite_de_nuages_totaux": 6,
      "quantite_de_nuages_bas": 6,
      "type_de_nuages_bas": "3",
      "indicateur_de_hauteur_de_nuages": null,
      "hauteur_de_nuages": "5",
      "type_de_nuages_moyens": "0",
      "type_de_nuages_elevés": "0",
      "direction_des_vagues": null,
      "periode_des_vagues": 0,
      "hauteur_des_vagues": 0.0,
      "direction_de_houle": 23,
      "periode_de_houle": 2,
      "hauteur_de_houle": 0.5,
      "indicateur_de_systeme_de_boites": "",
      "numero_de_boite_de_dix_degres": 333,
      "numero_de_boite_de_un_degre": 42,
      "pont": 992,
      "source_id": 114,
      "type_de_plateforme": 5,
      "statut_de_doublon": 1,
      "verif_de_doublon": 2,
      "verif_de_trajectoire": null,
      "biais_de_pression": null,
      "indicateur_de_periode_de_vagues": null,
      "indicateur_de_periode_de_houle": null,
      "second_code_de_pays": null,
      "flags_de_qc_adaptatif": "",
      "flag_jour_nuit": 2,
      "flags_de_rognage": "131111",
      "flags_de_qc_ncdc": "11111111111111",
      "externe": null,
      "flag_de_mer_interieure": null,
      "flags_dexclusion_de_source": null,
      "id_de_rapport_unique": "CUQHE1",
      "numero_de_liberation_primaire": 3,
      "numero_de_liberation_secondaire": 0,
      "numero_de_liberation_tertiaire": 0,
      "indicateur_de_statut_de_liberation": 2,
      "flag_de_rejet_intermediaire": 1,
      "timestamp": "2014-11-29 02:00:00+00:00"
    },
    {
      "année": 2014,
      "mois": 11,
      "jour": 3,
      "heure": 18.0,
      "latitude": 49.6,
      "longitude": -16.1,
      "imma_version": 1,
      "attm_count": 4,
      "indicateur_de_temps": 0,
      "indicateur_de_latlong": 0,
      "cap_de_navire": 7,
      "vitesse_de_navire": 4,
      "indicateur_de_source_nationale": null,
      "id_indicator": 1,
      "callsign": "3EMS",
      "code_de_pays": "",
      "indicateur_de_direction_de_vent": 0,
      "direction_de_vent_vrai": 310,
      "indicateur_de_vitesse_de_vent": 4,
      "vitesse_de_vent": 17.5,
      "indicateur_de_visibilite": null,
      "visibilite": 97,
      "temps_actuel": 1,
      "temps_passe": 5,
      "pression_au_niveau_de_la_mer": 1005.0,
      "caracteristique_de_ppp": 4,
      "amt_pressure_tend": 0.0,
      "indicateur_de_temperature": 0,
      "temperature_de_lair": 11.0,
      "wbt_indicator": 0,
      "temperature_de_bulbe_humide": 8.5,
      "dpt_indicator": null,
      "temperature_de_point_de_rosee": 6.1,
      "methode_de_mesure_de_la_temp_de_surface_de_la_mer": 1,
      "temperature_de_surface_de_la_mer": 14.0,
      "quantite_de_nuages_totaux": 4,
      "quantite_de_nuages_bas": 3,
      "type_de_nuages_bas": "3",
      "indicateur_de_hauteur_de_nuages": null,
      "hauteur_de_nuages": "4",
      "type_de_nuages_moyens": "0",
      "type_de_nuages_elevés": "0",
      "direction_des_vagues": null,
      "periode_des_vagues": 8,
      "hauteur_des_vagues": 3.5,
      "direction_de_houle": 34,
      "periode_de_houle": 7,
      "hauteur_de_houle": 2.5,
      "indicateur_de_systeme_de_boites": "",
      "numero_de_boite_de_dix_degres": 176,
      "numero_de_boite_de_un_degre": 96,
      "pont": 992,
      "source_id": 114,
      "type_de_plateforme": 5,
      "statut_de_doublon": 1,
      "verif_de_doublon": 2,
      "verif_de_trajectoire": null,
      "biais_de_pression": null,
      "indicateur_de_periode_de_vagues": null,
      "indicateur_de_periode_de_houle": null,
      "second_code_de_pays": null,
      "flags_de_qc_adaptatif": "",
      "flag_jour_nuit": 1,
      "flags_de_rognage": "111111",
      "flags_de_qc_ncdc": "11111111111111",
      "externe": null,
      "flag_de_mer_interieure": null,
      "flags_dexclusion_de_source": null,
      "id_de_rapport_unique": "CRANGB",
      "numero_de_liberation_primaire": 3,
      "numero_de_liberation_secondaire": 0,
      "numero_de_liberation_tertiaire": 0,
      "indicateur_de_statut_de_liberation": 2,
      "flag_de_rejet_intermediaire": 1,
      "timestamp": "2014-11-03 18:00:00+00:00"
    },
    {
      "année": 2014,
      "mois": 4,
      "jour": 1,
      "heure": 0.0,
      "latitude": 29.2,
      "longitude": -94.6,
      "imma_version": 1,
      "attm_count": 4,
      "indicateur_de_temps": 0,
      "indicateur_de_latlong": 0,
      "cap_de_navire": 0,
      "vitesse_de_navire": 0,
      "indicateur_de_source_nationale": null,
      "id_indicator": 1,
      "callsign": "3FUU",
      "code_de_pays": "",
      "indicateur_de_direction_de_vent": 0,
      "direction_de_vent_vrai": 130,
      "indicateur_de_vitesse_de_vent": 4,
      "vitesse_de_vent": 6.7,
      "indicateur_de_visibilite": null,
      "visibilite": 99,
      "temps_actuel": 3,
      "temps_passe": 2,
      "pression_au_niveau_de_la_mer": 1015.0,
      "caracteristique_de_ppp": 6,
      "amt_pressure_tend": 1.0,
      "indicateur_de_temperature": 0,
      "temperature_de_lair": 22.0,
      "wbt_indicator": 0,
      "temperature_de_bulbe_humide": 21.0,
      "dpt_indicator": null,
      "temperature_de_point_de_rosee": 20.5,
      "methode_de_mesure_de_la_temp_de_surface_de_la_mer": 1,
      "temperature_de_surface_de_la_mer": 22.0,
      "quantite_de_nuages_totaux": 5,
      "quantite_de_nuages_bas": 3,
      "type_de_nuages_bas": "6",
      "indicateur_de_hauteur_de_nuages": null,
      "hauteur_de_nuages": "4",
      "type_de_nuages_moyens": "4",
      "type_de_nuages_elevés": "3",
      "direction_des_vagues": null,
      "periode_des_vagues": 10,
      "hauteur_des_vagues": 1.0,
      "direction_de_houle": 23,
      "periode_de_houle": 9,
      "hauteur_de_houle": 1.0,
      "indicateur_de_systeme_de_boites": "",
      "numero_de_boite_de_dix_degres": 240,
      "numero_de_boite_de_un_degre": 94,
      "pont": 992,
      "source_id": 114,
      "type_de_plateforme": 5,
      "statut_de_doublon": 1,
      "verif_de_doublon": 2,
      "verif_de_trajectoire": null,
      "biais_de_pression": null,
      "indicateur_de_periode_de_vagues": null,
      "indicateur_de_periode_de_houle": null,
      "second_code_de_pays": null,
      "flags_de_qc_adaptatif": "",
      "flag_jour_nuit": 2,
      "flags_de_rognage": "111111",
      "flags_de_qc_ncdc": "11111111111111",
      "externe": null,
      "flag_de_mer_interieure": null,
      "flags_dexclusion_de_source": null,
      "id_de_rapport_unique": "BY8QUB",
      "numero_de_liberation_primaire": 3,
      "numero_de_liberation_secondaire": 0,
      "numero_de_liberation_tertiaire": 0,
      "indicateur_de_statut_de_liberation": 2,
      "flag_de_rejet_intermediaire": 1,
      "timestamp": "2014-04-01 00:00:00+00:00"
    }
  ]
}