{
  "table_name": "USPTO_OCE_OFFICE_ACTIONS.OFFICE_ACTIONS",
  "table_fullname": "PATENTS_USPTO.USPTO_OCE_OFFICE_ACTIONS.OFFICE_ACTIONS",
  "column_names": [
    "refus_dp",
    "fermeture_manquante",
    "refus_103",
    "fp_manquante",
    "demandes_autorisees",
    "refus_112",
    "app_id",
    "cite103_eq1",
    "entete_manquante",
    "cite103_max",
    "art_unit",
    "refus_fp_incompatibilite",
    "uspc_class",
    "refus_101",
    "cite103_gt3",
    "uspc_sous_classe",
    "ifw_number",
    "signature_type",
    "refus_102",
    "cite102_gt1",
    "objection",
    "mail_dt",
    "document_cd"
  ],
  "column_types": [
    "TEXT",
    "TEXT",
    "TEXT",
    "TEXT",
    "TEXT",
    "TEXT",
    "TEXT",
    "TEXT",
    "TEXT",
    "TEXT",
    "TEXT",
    "TEXT",
    "TEXT",
    "TEXT",
    "TEXT",
    "TEXT",
    "TEXT",
    "TEXT",
    "TEXT",
    "TEXT",
    "TEXT",
    "TEXT",
    "TEXT"
  ],
  "description": [
    null,
    null,
    null,
    null,
    null,
    null,
    null,
    null,
    null,
    null,
    null,
    null,
    null,
    null,
    null,
    null,
    null,
    null,
    null,
    null,
    null,
    null,
    null
  ],
  "sample_rows": [
    {
      "app_id": "13759138",
      "ifw_number": "HJZTZNLTPXXIFW4",
      "document_cd": "CTFR",
      "mail_dt": "2013-08-05",
      "art_unit": "1612",
      "uspc_class": "424",
      "uspc_sous_classe": "400000",
      "entete_manquante": "0",
      "fp_manquante": "1",
      "refus_fp_incompatibilite": "0",
      "fermeture_manquante": "0",
      "refus_101": "0",
      "refus_102": "1",
      "refus_103": "0",
      "refus_112": "1",
      "refus_dp": "0",
      "objection": "0",
      "demandes_autorisees": "0",
      "cite102_gt1": "1",
      "cite103_gt3": "0",
      "cite103_eq1": "0",
      "cite103_max": "0",
      "signature_type": "1"
    },
    {
      "app_id": "13375148",
      "ifw_number": "HPE42TOCPXXIFW4",
      "document_cd": "CTNF",
      "mail_dt": "2013-12-23",
      "art_unit": "1612",
      "uspc_class": "424",
      "uspc_sous_classe": "049000",
      "entete_manquante": "1",
      "fp_manquante": "1",
      "refus_fp_incompatibilite": "0",
      "fermeture_manquante": "0",
      "refus_101": "0",
      "refus_102": "1",
      "refus_103": "0",
      "refus_112": "1",
      "refus_dp": "0",
      "objection": "0",
      "demandes_autorisees": "0",
      "cite102_gt1": "0",
      "cite103_gt3": "0",
      "cite103_eq1": "0",
      "cite103_max": "0",
      "signature_type": "0"
    },
    {
      "app_id": "12598395",
      "ifw_number": "H03V6DB6PXXIFW4",
      "document_cd": "CTNF",
      "mail_dt": "2012-03-26",
      "art_unit": "1615",
      "uspc_class": "424",
      "uspc_sous_classe": "457000",
      "entete_manquante": "0",
      "fp_manquante": "0",
      "refus_fp_incompatibilite": "0",
      "fermeture_manquante": "0",
      "refus_101": "0",
      "refus_102": "1",
      "refus_103": "0",
      "refus_112": "1",
      "refus_dp": "1",
      "objection": "0",
      "demandes_autorisees": "0",
      "cite102_gt1": "1",
      "cite103_gt3": "0",
      "cite103_eq1": "0",
      "cite103_max": "0",
      "signature_type": "0"
    },
    {
      "app_id": "12491560",
      "ifw_number": "H7LZTTS4PXXIFW4",
      "document_cd": "CTFR",
      "mail_dt": "2012-09-27",
      "art_unit": "1617",
      "uspc_class": "424",
      "uspc_sous_classe": "070280",
      "entete_manquante": "1",
      "fp_manquante": "1",
      "refus_fp_incompatibilite": "0",
      "fermeture_manquante": "0",
      "refus_101": "0",
      "refus_102": "1",
      "refus_103": "0",
      "refus_112": "0",
      "refus_dp": "1",
      "objection": "0",
      "demandes_autorisees": "0",
      "cite102_gt1": "0",
      "cite103_gt3": "0",
      "cite103_eq1": "0",
      "cite103_max": "0",
      "signature_type": "2"
    },
    {
      "app_id": "14215930",
      "ifw_number": "IQLCOQDCRXEAPX2",
      "document_cd": "CTNF",
      "mail_dt": "2016-07-15",
      "art_unit": "1618",
      "uspc_class": "424",
      "uspc_sous_classe": "009600",
      "entete_manquante": "1",
      "fp_manquante": "0",
      "refus_fp_incompatibilite": "0",
      "fermeture_manquante": "0",
      "refus_101": "0",
      "refus_102": "0",
      "refus_103": "0",
      "refus_112": "1",
      "refus_dp": "0",
      "objection": "1",
      "demandes_autorisees": "0",
      "cite102_gt1": "0",
      "cite103_gt3": "0",
      "cite103_eq1": "0",
      "cite103_max": "0",
      "signature_type": "1"
    }
  ]
}