{
  "table_name": "ghcnd_1870",
  "table_fullname": "bigquery-public-data.ghcn_d.ghcnd_1870",
  "column_names": [
    "Identifikator",
    "Datum",
    "Element",
    "Wert",
    "M-Kennzeichen",
    "Q-Kennzeichen",
    "S-Kennzeichen",
    "Zeit"
  ],
  "column_types": [
    "STRING",
    "DATE",
    "STRING",
    "FLOAT64",
    "STRING",
    "STRING",
    "STRING",
    "STRING"
  ],
  "nested_column_names": [
    "Identifikator",
    "Datum",
    "Element",
    "Wert",
    "M-Kennzeichen",
    "Q-Kennzeichen",
    "S-Kennzeichen",
    "Zeit"
  ],
  "nested_column_types": [
    "STRING",
    "DATE",
    "STRING",
    "FLOAT64",
    "STRING",
    "STRING",
    "STRING",
    "STRING"
  ],
  "description": [
    null,
    null,
    null,
    null,
    null,
    null,
    null,
    null
  ],
  "sample_rows": [
    {
      "Identifikator": "USC00298072",
      "Datum": "1870-01-16",
      "Element": "PRCP",
      "Wert": 0.0,
      "M-Kennzeichen": null,
      "Q-Kennzeichen": null,
      "S-Kennzeichen": "0",
      "Zeit": null
    },
    {
      "Identifikator": "USC00298072",
      "Datum": "1870-04-24",
      "Element": "PRCP",
      "Wert": 0.0,
      "M-Kennzeichen": null,
      "Q-Kennzeichen": null,
      "S-Kennzeichen": "0",
      "Zeit": null
    },
    {
      "Identifikator": "USC00298072",
      "Datum": "1870-05-24",
      "Element": "PRCP",
      "Wert": 0.0,
      "M-Kennzeichen": null,
      "Q-Kennzeichen": null,
      "S-Kennzeichen": "0",
      "Zeit": null
    },
    {
      "Identifikator": "USC00298072",
      "Datum": "1870-06-12",
      "Element": "PRCP",
      "Wert": 0.0,
      "M-Kennzeichen": null,
      "Q-Kennzeichen": null,
      "S-Kennzeichen": "0",
      "Zeit": null
    },
    {
      "Identifikator": "USC00298072",
      "Datum": "1870-07-29",
      "Element": "PRCP",
      "Wert": 0.0,
      "M-Kennzeichen": null,
      "Q-Kennzeichen": null,
      "S-Kennzeichen": "0",
      "Zeit": null
    }
  ]
}